[
    {
        "2023": "2,658513982",
        "2024": "1,329256991",
        "2025": "0",
        "2026": "0",
        "2027": "0",
        "2028": "0",
        "2029": "0",
        "2030": "0",
        "2031": "0",
        "2032": "0",
        "2033": "0",
        "2034": "0",
        "2035": "0",
        "2036": "0",
        "2037": "0",
        "2038": "0",
        "2039": "0",
        "2040": "0",
        "2041": "0",
        "2042": "0",
        "2043": "0",
        "2044": "0",
        "2045": "0",
        "2046": "0",
        "2047": "0",
        "2048": "0",
        "2049": "0",
        "2050": "0",
        "Model": "DREEM",
        "Scenario": "familiar_world",
        "Region": "MEGALOPOLIS-GREECE",
        "Variable": "Energy Mix|Residential and Commercial|Residential|Oil Products (Heating)",
        "Unit": "ktoe/yr"
    },
    {
        "2023": "1,117876655",
        "2024": "1,117876655",
        "2025": "1,117876655",
        "2026": "1,117876655",
        "2027": "1,117876655",
        "2028": "1,117876655",
        "2029": "1,117876655",
        "2030": "1,117876655",
        "2031": "1,110963929",
        "2032": "1,117876655",
        "2033": "1,117876655",
        "2034": "1,117876655",
        "2035": "1,117876655",
        "2036": "1,16928319",
        "2037": "1,220689725",
        "2038": "1,27209626",
        "2039": "1,323502794",
        "2040": "1,374909329",
        "2041": "1,426315864",
        "2042": "1,477722399",
        "2043": "1,529128934",
        "2044": "1,578460081",
        "2045": "1,58664419",
        "2046": "1,594828299",
        "2047": "1,603012408",
        "2048": "1,611196517",
        "2049": "1,619380626",
        "2050": "1,627564735",
        "Model": "DREEM",
        "Scenario": "familiar_world",
        "Region": "MEGALOPOLIS-GREECE",
        "Variable": "Energy Mix|Residential and Commercial|Residential|Electricity",
        "Unit": "ktoe/yr"
    },
    {
        "2023": "0",
        "2024": "1,439707834",
        "2025": "2,879415668",
        "2026": "2,845837023",
        "2027": "2,763531011",
        "2028": "2,778679733",
        "2029": "2,745101088",
        "2030": "2,711522443",
        "2031": "2,677943799",
        "2032": "2,644365154",
        "2033": "2,610786509",
        "2034": "2,577207864",
        "2035": "2,543629219",
        "2036": "2,313612377",
        "2037": "2,083595535",
        "2038": "1,853578693",
        "2039": "1,623561851",
        "2040": "1,393545008",
        "2041": "1,163528166",
        "2042": "0,933511324",
        "2043": "0,703494482",
        "2044": "0,480675512",
        "2045": "0,400562926",
        "2046": "0,320450341",
        "2047": "0,240337756",
        "2048": "0,160225171",
        "2049": "0,080112585",
        "2050": "0",
        "Model": "DREEM",
        "Scenario": "familiar_world",
        "Region": "MEGALOPOLIS-GREECE",
        "Variable": "Energy Mix|Residential and Commercial|Residential|Natural Gas",
        "Unit": "ktoe/yr"
    },
    {
        "2023": "0,85672804",
        "2024": "0,42836402",
        "2025": "0",
        "2026": "0",
        "2027": "0",
        "2028": "0",
        "2029": "0",
        "2030": "0",
        "2031": "0",
        "2032": "0",
        "2033": "0",
        "2034": "0",
        "2035": "0",
        "2036": "0",
        "2037": "0",
        "2038": "0",
        "2039": "0",
        "2040": "0",
        "2041": "0",
        "2042": "0",
        "2043": "0",
        "2044": "0",
        "2045": "0",
        "2046": "0",
        "2047": "0",
        "2048": "0",
        "2049": "0",
        "2050": "0",
        "Model": "DREEM",
        "Scenario": "familiar_world",
        "Region": "MEGALOPOLIS-GREECE",
        "Variable": "Energy Mix|Residential and Commercial|Residential|District Heating",
        "Unit": "ktoe/yr"
    },
    {
        "2023": "0,090549976",
        "2024": "0,045274988",
        "2025": "0",
        "2026": "0",
        "2027": "0",
        "2028": "0",
        "2029": "0",
        "2030": "0",
        "2031": "0",
        "2032": "0",
        "2033": "0",
        "2034": "0",
        "2035": "0",
        "2036": "0",
        "2037": "0",
        "2038": "0",
        "2039": "0",
        "2040": "0",
        "2041": "0",
        "2042": "0",
        "2043": "0",
        "2044": "0",
        "2045": "0",
        "2046": "0",
        "2047": "0",
        "2048": "0",
        "2049": "0",
        "2050": "0",
        "Model": "DREEM",
        "Scenario": "familiar_world",
        "Region": "MEGALOPOLIS-GREECE",
        "Variable": "Energy Mix|Residential and Commercial|Residential|Biomass",
        "Unit": "ktoe/yr"
    },
    {
        "2023": "0",
        "2024": "0,363188165",
        "2025": "0,72637633",
        "2026": "0,759954975",
        "2027": "0,842260987",
        "2028": "0,827112264",
        "2029": "0,860690909",
        "2030": "0,894269554",
        "2031": "0,934760925",
        "2032": "0,961426844",
        "2033": "0,995005489",
        "2034": "1,028584134",
        "2035": "1,062162779",
        "2036": "1,240773086",
        "2037": "1,419383393",
        "2038": "1,597993701",
        "2039": "1,776604008",
        "2040": "1,955214315",
        "2041": "2,133824622",
        "2042": "2,31243493",
        "2043": "2,491045237",
        "2044": "2,66453306",
        "2045": "2,736461537",
        "2046": "2,808390013",
        "2047": "2,880318489",
        "2048": "2,952246966",
        "2049": "3,024175442",
        "2050": "3,096103918",
        "Model": "DREEM",
        "Scenario": "familiar_world",
        "Region": "MEGALOPOLIS-GREECE",
        "Variable": "Final Energy|Residential and Commercial|Residential|Savings",
        "Unit": "ktoe/yr"
    },
    {
        "2023": "2,658513982",
        "2024": "1,329256991",
        "2025": "0",
        "2026": "0",
        "2027": "0",
        "2028": "0",
        "2029": "0",
        "2030": "0",
        "2031": "0",
        "2032": "0",
        "2033": "0",
        "2034": "0",
        "2035": "0",
        "2036": "0",
        "2037": "0",
        "2038": "0",
        "2039": "0",
        "2040": "0",
        "2041": "0",
        "2042": "0",
        "2043": "0",
        "2044": "0",
        "2045": "0",
        "2046": "0",
        "2047": "0",
        "2048": "0",
        "2049": "0",
        "2050": "0",
        "Model": "DREEM",
        "Scenario": "fragmented_world",
        "Region": "MEGALOPOLIS-GREECE",
        "Variable": "Energy Mix|Residential and Commercial|Residential|Oil Products (Heating)",
        "Unit": "ktoe/yr"
    },
    {
        "2023": "1,117876655",
        "2024": "1,117876655",
        "2025": "1,117876655",
        "2026": "1,117876655",
        "2027": "1,117876655",
        "2028": "1,117876655",
        "2029": "1,117876655",
        "2030": "1,117876655",
        "2031": "1,110963929",
        "2032": "1,117876655",
        "2033": "1,117876655",
        "2034": "1,117876655",
        "2035": "1,117876655",
        "2036": "1,117876655",
        "2037": "1,117876655",
        "2038": "1,117876655",
        "2039": "1,117876655",
        "2040": "1,117876655",
        "2041": "1,143579923",
        "2042": "1,16928319",
        "2043": "1,194986457",
        "2044": "1,220689725",
        "2045": "1,246392992",
        "2046": "1,27209626",
        "2047": "1,297799527",
        "2048": "1,323502794",
        "2049": "1,349206062",
        "2050": "1,374909329",
        "Model": "DREEM",
        "Scenario": "fragmented_world",
        "Region": "MEGALOPOLIS-GREECE",
        "Variable": "Energy Mix|Residential and Commercial|Residential|Electricity",
        "Unit": "ktoe/yr"
    },
    {
        "2023": "0",
        "2024": "1,439707834",
        "2025": "2,879415668",
        "2026": "2,845837023",
        "2027": "2,763531011",
        "2028": "2,778679733",
        "2029": "2,745101088",
        "2030": "2,711522443",
        "2031": "2,677943799",
        "2032": "2,644365154",
        "2033": "2,610786509",
        "2034": "2,577207864",
        "2035": "2,543629219",
        "2036": "2,510050574",
        "2037": "2,476471929",
        "2038": "2,442893284",
        "2039": "2,409314639",
        "2040": "2,375735994",
        "2041": "2,243938251",
        "2042": "2,112140507",
        "2043": "1,980342764",
        "2044": "1,84854502",
        "2045": "1,716747277",
        "2046": "1,584949533",
        "2047": "1,45315179",
        "2048": "1,321354046",
        "2049": "1,189556303",
        "2050": "1,057758559",
        "Model": "DREEM",
        "Scenario": "fragmented_world",
        "Region": "MEGALOPOLIS-GREECE",
        "Variable": "Energy Mix|Residential and Commercial|Residential|Natural Gas",
        "Unit": "ktoe/yr"
    },
    {
        "2023": "0,85672804",
        "2024": "0,42836402",
        "2025": "0",
        "2026": "0",
        "2027": "0",
        "2028": "0",
        "2029": "0",
        "2030": "0",
        "2031": "0",
        "2032": "0",
        "2033": "0",
        "2034": "0",
        "2035": "0",
        "2036": "0",
        "2037": "0",
        "2038": "0",
        "2039": "0",
        "2040": "0",
        "2041": "0",
        "2042": "0",
        "2043": "0",
        "2044": "0",
        "2045": "0",
        "2046": "0",
        "2047": "0",
        "2048": "0",
        "2049": "0",
        "2050": "0",
        "Model": "DREEM",
        "Scenario": "fragmented_world",
        "Region": "MEGALOPOLIS-GREECE",
        "Variable": "Energy Mix|Residential and Commercial|Residential|District Heating",
        "Unit": "ktoe/yr"
    },
    {
        "2023": "0,090549976",
        "2024": "0,045274988",
        "2025": "0",
        "2026": "0",
        "2027": "0",
        "2028": "0",
        "2029": "0",
        "2030": "0",
        "2031": "0",
        "2032": "0",
        "2033": "0",
        "2034": "0",
        "2035": "0",
        "2036": "0",
        "2037": "0",
        "2038": "0",
        "2039": "0",
        "2040": "0",
        "2041": "0",
        "2042": "0",
        "2043": "0",
        "2044": "0",
        "2045": "0",
        "2046": "0",
        "2047": "0",
        "2048": "0",
        "2049": "0",
        "2050": "0",
        "Model": "DREEM",
        "Scenario": "fragmented_world",
        "Region": "MEGALOPOLIS-GREECE",
        "Variable": "Energy Mix|Residential and Commercial|Residential|Biomass",
        "Unit": "ktoe/yr"
    },
    {
        "2023": "0",
        "2024": "0,363188165",
        "2025": "0,72637633",
        "2026": "0,759954975",
        "2027": "0,842260987",
        "2028": "0,827112264",
        "2029": "0,860690909",
        "2030": "0,894269554",
        "2031": "0,934760925",
        "2032": "0,961426844",
        "2033": "0,995005489",
        "2034": "1,028584134",
        "2035": "1,062162779",
        "2036": "1,095741424",
        "2037": "1,129320069",
        "2038": "1,162898713",
        "2039": "1,196477358",
        "2040": "1,230056003",
        "2041": "1,336150479",
        "2042": "1,442244955",
        "2043": "1,548339432",
        "2044": "1,654433908",
        "2045": "1,760528384",
        "2046": "1,86662286",
        "2047": "1,972717336",
        "2048": "2,078811812",
        "2049": "2,184906288",
        "2050": "2,291000764",
        "Model": "DREEM",
        "Scenario": "fragmented_world",
        "Region": "MEGALOPOLIS-GREECE",
        "Variable": "Final Energy|Residential and Commercial|Residential|Savings",
        "Unit": "ktoe/yr"
    },
    {
        "2023": "2,658513982",
        "2024": "1,329256991",
        "2025": "0",
        "2026": "0",
        "2027": "0",
        "2028": "0",
        "2029": "0",
        "2030": "0",
        "2031": "0",
        "2032": "0",
        "2033": "0",
        "2034": "0",
        "2035": "0",
        "2036": "0",
        "2037": "0",
        "2038": "0",
        "2039": "0",
        "2040": "0",
        "2041": "0",
        "2042": "0",
        "2043": "0",
        "2044": "0",
        "2045": "0",
        "2046": "0",
        "2047": "0",
        "2048": "0",
        "2049": "0",
        "2050": "0",
        "Model": "DREEM",
        "Scenario": "unified_world",
        "Region": "MEGALOPOLIS-GREECE",
        "Variable": "Energy Mix|Residential and Commercial|Residential|Oil Products (Heating)",
        "Unit": "ktoe/yr"
    },
    {
        "2023": "1,117876655",
        "2024": "1,493743817",
        "2025": "1,869610978",
        "2026": "1,859929128",
        "2027": "1,850247279",
        "2028": "1,840565429",
        "2029": "1,830883579",
        "2030": "1,821201729",
        "2031": "1,870207928",
        "2032": "1,80183803",
        "2033": "1,79215618",
        "2034": "1,78247433",
        "2035": "1,772792481",
        "2036": "1,763110631",
        "2037": "1,753428781",
        "2038": "1,743746932",
        "2039": "1,734065082",
        "2040": "1,724383232",
        "2041": "1,714701382",
        "2042": "1,705019533",
        "2043": "1,695337683",
        "2044": "1,685655833",
        "2045": "1,675973983",
        "2046": "1,666292134",
        "2047": "1,656610284",
        "2048": "1,705616482",
        "2049": "1,637246584",
        "2050": "1,627564735",
        "Model": "DREEM",
        "Scenario": "unified_world",
        "Region": "MEGALOPOLIS-GREECE",
        "Variable": "Energy Mix|Residential and Commercial|Residential|Electricity",
        "Unit": "ktoe/yr"
    },
    {
        "2023": "0",
        "2024": "0",
        "2025": "0",
        "2026": "0",
        "2027": "0",
        "2028": "0",
        "2029": "0",
        "2030": "0",
        "2031": "0",
        "2032": "0",
        "2033": "0",
        "2034": "0",
        "2035": "0",
        "2036": "0",
        "2037": "0",
        "2038": "0",
        "2039": "0",
        "2040": "0",
        "2041": "0",
        "2042": "0",
        "2043": "0",
        "2044": "0",
        "2045": "0",
        "2046": "0",
        "2047": "0",
        "2048": "0",
        "2049": "0",
        "2050": "0",
        "Model": "DREEM",
        "Scenario": "unified_world",
        "Region": "MEGALOPOLIS-GREECE",
        "Variable": "Energy Mix|Residential and Commercial|Residential|Natural Gas",
        "Unit": "ktoe/yr"
    },
    {
        "2023": "0,85672804",
        "2024": "0,42836402",
        "2025": "0",
        "2026": "0",
        "2027": "0",
        "2028": "0",
        "2029": "0",
        "2030": "0",
        "2031": "0",
        "2032": "0",
        "2033": "0",
        "2034": "0",
        "2035": "0",
        "2036": "0",
        "2037": "0",
        "2038": "0",
        "2039": "0",
        "2040": "0",
        "2041": "0",
        "2042": "0",
        "2043": "0",
        "2044": "0",
        "2045": "0",
        "2046": "0",
        "2047": "0",
        "2048": "0",
        "2049": "0",
        "2050": "0",
        "Model": "DREEM",
        "Scenario": "unified_world",
        "Region": "MEGALOPOLIS-GREECE",
        "Variable": "Energy Mix|Residential and Commercial|Residential|District Heating",
        "Unit": "ktoe/yr"
    },
    {
        "2023": "0,090549976",
        "2024": "0,045274988",
        "2025": "0",
        "2026": "0",
        "2027": "0",
        "2028": "0",
        "2029": "0",
        "2030": "0",
        "2031": "0",
        "2032": "0",
        "2033": "0",
        "2034": "0",
        "2035": "0",
        "2036": "0",
        "2037": "0",
        "2038": "0",
        "2039": "0",
        "2040": "0",
        "2041": "0",
        "2042": "0",
        "2043": "0",
        "2044": "0",
        "2045": "0",
        "2046": "0",
        "2047": "0",
        "2048": "0",
        "2049": "0",
        "2050": "0",
        "Model": "DREEM",
        "Scenario": "unified_world",
        "Region": "MEGALOPOLIS-GREECE",
        "Variable": "Energy Mix|Residential and Commercial|Residential|Biomass",
        "Unit": "ktoe/yr"
    },
    {
        "2023": "0",
        "2024": "1,427028837",
        "2025": "2,854057675",
        "2026": "2,863739525",
        "2027": "2,873421374",
        "2028": "2,883103224",
        "2029": "2,892785074",
        "2030": "2,902466923",
        "2031": "2,853460725",
        "2032": "2,921830623",
        "2033": "2,931512473",
        "2034": "2,941194322",
        "2035": "2,950876172",
        "2036": "2,960558022",
        "2037": "2,970239872",
        "2038": "2,979921721",
        "2039": "2,989603571",
        "2040": "2,999285421",
        "2041": "3,008967271",
        "2042": "3,01864912",
        "2043": "3,02833097",
        "2044": "3,03801282",
        "2045": "3,047694669",
        "2046": "3,057376519",
        "2047": "3,067058369",
        "2048": "3,018052171",
        "2049": "3,086422068",
        "2050": "3,096103918",
        "Model": "DREEM",
        "Scenario": "unified_world",
        "Region": "MEGALOPOLIS-GREECE",
        "Variable": "Final Energy|Residential and Commercial|Residential|Savings",
        "Unit": "ktoe/yr"
    },
    {
        "2023": "13898,69969",
        "2024": "12809,49549",
        "2025": "11720,29129",
        "2026": "11050,42844",
        "2027": "10266,91065",
        "2028": "9710,702742",
        "2029": "9040,839894",
        "2030": "8370,977045",
        "2031": "7692,117382",
        "2032": "7553,789079",
        "2033": "7405,263133",
        "2034": "7256,737186",
        "2035": "7108,211239",
        "2036": "6552,317751",
        "2037": "5989,967397",
        "2038": "5421,160177",
        "2039": "4845,89609",
        "2040": "4264,175137",
        "2041": "3675,997317",
        "2042": "3031,4558",
        "2043": "2480,271078",
        "2044": "1888,502535",
        "2045": "1605,976777",
        "2046": "1322,423062",
        "2047": "1037,841389",
        "2048": "752,2317604",
        "2049": "465,5941746",
        "2050": "177,9286319",
        "Model": "DREEM",
        "Scenario": "familiar_world",
        "Region": "MEGALOPOLIS-GREECE",
        "Variable": "Emissions|CO2|Residential and Commercial|Residential",
        "Unit": "t CO2/yr"
    },
    {
        "2023": "13898,69969",
        "2024": "12809,49549",
        "2025": "11720,29129",
        "2026": "11050,42844",
        "2027": "10266,91065",
        "2028": "9710,702742",
        "2029": "9040,839894",
        "2030": "8370,977045",
        "2031": "7692,117382",
        "2032": "7553,789079",
        "2033": "7405,263133",
        "2034": "7256,737186",
        "2035": "7108,211239",
        "2036": "6959,685293",
        "2037": "6811,159346",
        "2038": "6662,633399",
        "2039": "6514,107452",
        "2040": "6365,581506",
        "2041": "6005,300706",
        "2042": "5634,661925",
        "2043": "5275,053806",
        "2044": "4905,087706",
        "2045": "4531,893173",
        "2046": "4155,470207",
        "2047": "3775,818807",
        "2048": "3392,938974",
        "2049": "3006,830709",
        "2050": "2617,49401",
        "Model": "DREEM",
        "Scenario": "fragmented_world",
        "Region": "MEGALOPOLIS-GREECE",
        "Variable": "Emissions|CO2|Residential and Commercial|Residential",
        "Unit": "t CO2/yr"
    },
    {
        "2023": "13898,69969",
        "2024": "11332,8829",
        "2025": "8369,274224",
        "2026": "7341,723245",
        "2027": "6324,41887",
        "2028": "5317,361096",
        "2029": "4320,549925",
        "2030": "3333,985356",
        "2031": "2434,04905",
        "2032": "2233,843112",
        "2033": "2109,288969",
        "2034": "1985,950905",
        "2035": "1863,82892",
        "2036": "1742,923014",
        "2037": "1623,233187",
        "2038": "1504,75944",
        "2039": "1387,501771",
        "2040": "1271,460181",
        "2041": "1156,63467",
        "2042": "959,1875317",
        "2043": "930,6318863",
        "2044": "819,4546128",
        "2045": "709,4934183",
        "2046": "600,748303",
        "2047": "493,2192666",
        "2048": "400,6936577",
        "2049": "281,8094311",
        "2050": "177,9286319",
        "Model": "DREEM",
        "Scenario": "unified_world",
        "Region": "MEGALOPOLIS-GREECE",
        "Variable": "Emissions|CO2|Residential and Commercial|Residential",
        "Unit": "t CO2/yr"
    },
    {
        "2023": "1871,300569",
        "2024": "4214,156802",
        "2025": "3995,508373",
        "2026": "1556,840793",
        "2027": "1581,473792",
        "2028": "1591,995659",
        "2029": "1590,424297",
        "2030": "1588,570042",
        "2031": "1581,370305",
        "2032": "1665,815135",
        "2033": "1656,947418",
        "2034": "1647,928664",
        "2035": "1638,758875",
        "2036": "2046,51133",
        "2037": "1988,692877",
        "2038": "1929,393313",
        "2039": "1868,612636",
        "2040": "1806,350847",
        "2041": "1742,607945",
        "2042": "1677,383932",
        "2043": "1634,633908",
        "2044": "1591,313126",
        "2045": "1565,11012",
        "2046": "1538,475685",
        "2047": "1511,409819",
        "2048": "1483,912524",
        "2049": "1455,983799",
        "2050": "1427,623644",
        "Model": "DREEM",
        "Scenario": "familiar_world",
        "Region": "MEGALOPOLIS-GREECE",
        "Variable": "Total Fuel Costs (Per Household)|Residential and Commercial|Residential",
        "Unit": "euros/household/yr"
    },
    {
        "2023": "2196,645506",
        "2024": "5561,860585",
        "2025": "6363,49075",
        "2026": "3947,776265",
        "2027": "3951,622411",
        "2028": "4016,130994",
        "2029": "4029,583471",
        "2030": "4041,702327",
        "2031": "4046,096097",
        "2032": "4124,457351",
        "2033": "4107,616202",
        "2034": "4090,063033",
        "2035": "4071,797847",
        "2036": "4052,820641",
        "2037": "4033,131417",
        "2038": "4012,730175",
        "2039": "3991,616913",
        "2040": "3969,791634",
        "2041": "4008,118356",
        "2042": "3871,21138",
        "2043": "3743,205399",
        "2044": "3612,122862",
        "2045": "3477,963769",
        "2046": "3340,72812",
        "2047": "3200,415915",
        "2048": "3057,027154",
        "2049": "2910,561838",
        "2050": "2761,019965",
        "Model": "DREEM",
        "Scenario": "fragmented_world",
        "Region": "MEGALOPOLIS-GREECE",
        "Variable": "Total Fuel Costs (Per Household)|Residential and Commercial|Residential",
        "Unit": "euros/household/yr"
    },
    {
        "2023": "1347,258289",
        "2024": "7078,243531",
        "2025": "6703,993759",
        "2026": "1124,439681",
        "2027": "1112,948612",
        "2028": "1101,520553",
        "2029": "1090,155503",
        "2030": "1078,853463",
        "2031": "1099,819066",
        "2032": "1056,438411",
        "2033": "1045,325398",
        "2034": "1034,275396",
        "2035": "1023,288403",
        "2036": "1012,364419",
        "2037": "1001,503445",
        "2038": "990,70548",
        "2039": "979,9705247",
        "2040": "969,2985787",
        "2041": "958,6896423",
        "2042": "948,1437152",
        "2043": "937,6607976",
        "2044": "927,2408895",
        "2045": "916,8839908",
        "2046": "906,5901016",
        "2047": "896,3592217",
        "2048": "915,1494813",
        "2049": "876,0864905",
        "2050": "866,044639",
        "Model": "DREEM",
        "Scenario": "unified_world",
        "Region": "MEGALOPOLIS-GREECE",
        "Variable": "Total Fuel Costs (Per Household)|Residential and Commercial|Residential",
        "Unit": "euros/household/yr"
    },
    {
        "2023": "6633760,516",
        "2024": "14939185,86",
        "2025": "14164077,18",
        "2026": "5519000,612",
        "2027": "5606324,592",
        "2028": "5643624,61",
        "2029": "5638054,133",
        "2030": "5631480,798",
        "2031": "5605957,732",
        "2032": "5905314,653",
        "2033": "5873878,596",
        "2034": "5841907,115",
        "2035": "5809400,21",
        "2036": "7254882,665",
        "2037": "7049916,251",
        "2038": "6839699,293",
        "2039": "6624231,794",
        "2040": "6403513,751",
        "2041": "6177545,166",
        "2042": "5946326,038",
        "2043": "5794777,204",
        "2044": "5641205,031",
        "2045": "5548315,376",
        "2046": "5453896,302",
        "2047": "5357947,81",
        "2048": "5260469,898",
        "2049": "5161462,568",
        "2050": "5060925,819",
        "Model": "DREEM",
        "Scenario": "familiar_world",
        "Region": "MEGALOPOLIS-GREECE",
        "Variable": "Total Fuel Costs (All Households)|Residential and Commercial|Residential",
        "Unit": "euros/yr"
    },
    {
        "2023": "7787108,319",
        "2024": "19716795,77",
        "2025": "22558574,71",
        "2026": "13994866,86",
        "2027": "14008501,45",
        "2028": "14237184,37",
        "2029": "14284873,41",
        "2030": "14327834,75",
        "2031": "14343410,66",
        "2032": "14621201,31",
        "2033": "14561499,43",
        "2034": "14499273,45",
        "2035": "14434523,37",
        "2036": "14367249,17",
        "2037": "14297450,87",
        "2038": "14225128,47",
        "2039": "14150281,96",
        "2040": "14072911,34",
        "2041": "14208779,57",
        "2042": "13723444,34",
        "2043": "13269663,14",
        "2044": "12804975,55",
        "2045": "12329381,56",
        "2046": "11842881,19",
        "2047": "11345474,42",
        "2048": "10837161,26",
        "2049": "10317941,71",
        "2050": "9787815,774",
        "Model": "DREEM",
        "Scenario": "fragmented_world",
        "Region": "MEGALOPOLIS-GREECE",
        "Variable": "Total Fuel Costs (All Households)|Residential and Commercial|Residential",
        "Unit": "euros/yr"
    },
    {
        "2023": "4776030,636",
        "2024": "25092373,32",
        "2025": "23765657,88",
        "2026": "3986138,669",
        "2027": "3945402,831",
        "2028": "3904890,361",
        "2029": "3864601,259",
        "2030": "3824535,526",
        "2031": "3898858,588",
        "2032": "3745074,165",
        "2033": "3705678,538",
        "2034": "3666506,279",
        "2035": "3627557,388",
        "2036": "3588831,866",
        "2037": "3550329,712",
        "2038": "3512050,927",
        "2039": "3473995,51",
        "2040": "3436163,462",
        "2041": "3398554,782",
        "2042": "3361169,47",
        "2043": "3324007,528",
        "2044": "3287068,953",
        "2045": "3250353,747",
        "2046": "3213861,91",
        "2047": "3177593,441",
        "2048": "3244204,911",
        "2049": "3105726,609",
        "2050": "3070128,245",
        "Model": "DREEM",
        "Scenario": "unified_world",
        "Region": "MEGALOPOLIS-GREECE",
        "Variable": "Total Fuel Costs (All Households)|Residential and Commercial|Residential",
        "Unit": "euros/yr"
    }
]